alto/__init__.py
alto/alto_logger.py
alto/command.py
alto/config.py
alto/constants.py
alto/entrypoints.py
alto/infras.py
alto/main.py
alto/output.py
alto/ui.py
alto/utils.py
alto/agents/__init__.py
alto/agents/base.py
alto/agents/meta.py
alto/agents/ec2/__init__.py
alto/agents/ec2/ec2.py
alto/agents/ec2/protocols/__init__.py
alto/agents/ec2/protocols/base.py
alto/agents/ec2/protocols/ssh.py
alto/agents/ec2/protocols/ssm.py
alto/agents/scripts/__init__.py
alto/agents/scripts/docker/Dockerfile
alto/agents/scripts/docker/ec2/apply.sh
alto/agents/scripts/docker/ec2/run.sh
alto/agents/scripts/ec2/apply.sh
alto/agents/scripts/ec2/run.sh
alto/examples/__init__.py
alto/examples/ec2/artifacts.yml
alto/examples/ec2/basic_function.yml
alto/examples/ec2/basic_jupyter.yml
alto/examples/ec2/basic_project.yml
alto/examples/ec2/basic_script.yml
alto/examples/ec2/env_vars.yml
alto/examples/ec2/matrix.yml
alto/examples/ec2/mounts.yml
alto/images/__init__.py
alto/images/docker_image.py
alto/images/meta.py
alto/images/registries.py
alto/mixins/__init__.py
alto/mixins/aws_mixins.py
alto/parsers/yml.py
alto/tasks/__init__.py
alto/tasks/apply.py
alto/tasks/base.py
alto/tasks/build.py
alto/tasks/delete.py
alto/tasks/init.py
alto/tasks/run.py
alto/templates/__init__.py
alto/templates/common.yml
alto/templates/entrypoints/function.yml
alto/templates/entrypoints/jupyter.yml
alto/templates/entrypoints/project.yml
alto/templates/entrypoints/script.yml
alto/templates/infra/ec2-docker.yml
alto/templates/infra/ec2.yml
alto/tests/test_base_task.py
alto/tests/test_entrypoint.py
alto/tests/test_infras.py
alto/tests/test_init.py
alto/tests/test_utils.py
alto/tests/test_yml_parser.py
alto/tests/confs/bad_entrypoint.yml
alto/tests/confs/bad_env.yml
alto/tests/confs/bad_mounts.yml
alto/tests/confs/bad_python_version_format.yml
alto/tests/confs/bad_requirements.yml
alto/tests/confs/infra_bad_type.yml
alto/tests/confs/infra_no_type.yml
alto/tests/confs/no_entrypoint.yml
alto/tests/confs/no_infra.yml
alto_dev-0.0.8.dist-info/LICENSE
alto_dev-0.0.8.dist-info/METADATA
alto_dev-0.0.8.dist-info/WHEEL
alto_dev-0.0.8.dist-info/entry_points.txt
alto_dev-0.0.8.dist-info/top_level.txt
alto_dev-0.0.8.dist-info/RECORD
